ADS1115/__init__.py
ADS1115-0.2.1.dist-info/METADATA
ADS1115-0.2.1.dist-info/WHEEL
ADS1115-0.2.1.dist-info/top_level.txt
ADS1115-0.2.1.dist-info/RECORD
